README.rst
setup.py
crispy_bootstrap/__init__.py
crispy_bootstrap/models.py
crispy_bootstrap/tests.py
crispy_bootstrap/views.py
crispy_bootstrap/static/crispy_bootstrap/crispy_bootstrap.css
crispy_bootstrap/static/crispy_bootstrap/crispy_bootstrap.scss
crispy_bootstrap/templates/bootstrap3/field.html
django_crispy_bootstrap.egg-info/PKG-INFO
django_crispy_bootstrap.egg-info/SOURCES.txt
django_crispy_bootstrap.egg-info/dependency_links.txt
django_crispy_bootstrap.egg-info/top_level.txt