Metadata-Version: 1.0
Name: django-crispy-bootstrap
Version: 0.1.1
Summary: UNKNOWN
Home-page: https://github.com/dimka665/django-crispy-bootstrap
Author: Dmitry Voronin
Author-email: dimka665@gmail.com
License: BSD
Platform: UNKNOWN
